suphia/__init__.py
suphia/__main__.py
suphia/cli.py
suphia/discovery.py
suphia/filesystem.py
suphia/skills/publish.py
suphia-0.1.1.dist-info/METADATA
suphia-0.1.1.dist-info/WHEEL
suphia-0.1.1.dist-info/entry_points.txt
suphia-0.1.1.dist-info/licenses/LICENSE
suphia-0.1.1.dist-info/RECORD
