Metadata-Version: 2.4
Name: suphia
Version: 0.1.1
Summary: A deterministic, cross-platform agent skill publisher.
License-File: LICENSE
Requires-Python: >=3.10
